yt/mcp/bin/__init__.py
yt/mcp/bin/mcp_yt_server.py
yt/mcp/lib/__init__.py
yt/mcp/lib/tool_runner_mcp.py
yt/mcp/lib/tools/__init__.py
yt/mcp/lib/tools/account.py
yt/mcp/lib/tools/admin.py
yt/mcp/lib/tools/check_is_paths_exists.py
yt/mcp/lib/tools/common_cypress.py
yt/mcp/lib/tools/get_attributes.py
yt/mcp/lib/tools/helpers.py
yt/mcp/lib/tools/list_dir.py
ytsaurus_mcp-0.1.0a1.dist-info/METADATA
ytsaurus_mcp-0.1.0a1.dist-info/WHEEL
ytsaurus_mcp-0.1.0a1.dist-info/entry_points.txt
ytsaurus_mcp-0.1.0a1.dist-info/top_level.txt
ytsaurus_mcp-0.1.0a1.dist-info/RECORD
