Metadata-Version: 2.1
Name: ytsaurus-mcp
Version: 0.1.0a1
Summary: MCP server for YT client.
Author: YTsaurus
Author-email: dev@ytsaurus.tech
License: Apache 2.0
Keywords: yt ytsaurus mcp server python client
Requires-Python: >=3.8
Requires-Dist: mcp>=1.7.1
Requires-Dist: pydantic>=2.10.4
Requires-Dist: ytsaurus-client
